[
  {
    "title": "Blue and white plaid beanie shell\nLL bean",
    "price": "",
    "url": "https://www.depop.com/products/shopy2z-blue-and-white-plaid-beanie/",
    "image": "https://media-photos.depop.com/b1/34544665/3157697475_65c502b3c9c345cba645546e45be859d/P0.jpg",
    "description": "Blue and white plaid beanie shell\nLL bean - Sold by @shopy2z",
    "category": "outerwear",
    "tag": "Depop find"
  },
  {
    "title": "Vera Bradley bag with 2 zipper compartments and 1...",
    "price": "",
    "url": "https://www.depop.com/products/zoessorenson-vera-bradley-bag-with-2/",
    "image": "https://media-photos.depop.com/b1/34544665/3156885948_ea31beb4d4d443668710b7549ca88b66/P0.jpg",
    "description": "Vera Bradley bag with 2 zipper compartments and 1 zipper pocket #VeraBradley\nSo adorable \nVintage - Sold by @shopy2z",
    "category": "accessories",
    "tag": "Depop find"
  },
  {
    "title": "Red Hollister Co. V-neck sweater \n\nVintage \nSizing...",
    "price": "",
    "url": "https://www.depop.com/products/zoessorenson-red-hollister-co-v-neck-sweater/",
    "image": "https://media-photos.depop.com/b1/34544665/3156880933_c5c2c841ed8b4fcf8aae3f82a0048b6d/P0.jpg",
    "description": "Red Hollister Co. V-neck sweater \n\nVintage \nSizing best fits a women\u2019s small - Sold by @shopy2z",
    "category": "tops",
    "tag": "Depop find"
  },
  {
    "title": "LL bean sweat shorts\nSize small",
    "price": "",
    "url": "https://www.depop.com/products/zoessorenson-ll-bean-sweat-shorts-size/",
    "image": "https://media-photos.depop.com/b1/34544665/3109706700_d0fb393dc2704837897b127c2d6a1d40/P0.jpg",
    "description": "LL bean sweat shorts\nSize small - Sold by @shopy2z",
    "category": "bottoms",
    "tag": "Depop find"
  },
  {
    "title": "Cropped white and black stripe sweater\nSuper cute...",
    "price": "",
    "url": "https://www.depop.com/products/zoessorenson-cropped-white-and-black-stripe/",
    "image": "https://media-photos.depop.com/b1/34544665/3081083372_cdc188864bbc4be89dd32551acd579af/P0.jpg",
    "description": "Cropped white and black stripe sweater\nSuper cute great for layering \nXs-s - Sold by @shopy2z",
    "category": "tops",
    "tag": "Depop find"
  },
  {
    "title": "Super cute brown and white sweater\n3/4 of the way...",
    "price": "",
    "url": "https://www.depop.com/products/zoessorenson-super-cute-brown-and-white/",
    "image": "https://media-photos.depop.com/b1/34544665/3069696416_6b55349fc5f647308bd4cf9896f05b40/P0.jpg",
    "description": "Super cute brown and white sweater\n3/4 of the way sleeves\nVintage #y2k \nFall girl\ud83c\udf42\nFits Xs-S - Sold by @shopy2z",
    "category": "tops",
    "tag": "Depop find"
  },
  {
    "title": "Cool pattern wind jacket shell\nMessage me before you...",
    "price": "",
    "url": "https://www.depop.com/products/zoessorenson-cool-pattern-wind-jacket-shell/",
    "image": "https://media-photos.depop.com/b1/34544665/3030475815_b81c1f148230453198136c838404f862/P0.jpg",
    "description": "Cool pattern wind jacket shell\nMessage me before you buy so I can un boost listing!\ud83d\ude04 - Sold by @shopy2z",
    "category": "outerwear",
    "tag": "Depop find"
  },
  {
    "title": "Black and gold pearl necklace and ring \nVintage...",
    "price": "",
    "url": "https://www.depop.com/products/zoessorenson-black-and-gold-pearl-necklace-adfc/",
    "image": "https://media-photos.depop.com/b1/34544665/3030620594_e8dbe41eadca419ca8f517c9ef6ba325/P0.jpg",
    "description": "Black and gold pearl necklace and ring \nVintage \nCute \nMessage me before buying so I can un boost!!\ud83d\ude3d - Sold by @shopy2z",
    "category": "accessories",
    "tag": "Depop find"
  },
  {
    "title": "Brown faux fur lined suede jacket with a boho vibe...",
    "price": "",
    "url": "https://www.depop.com/products/zoessorenson-brown-faux-fur-lined-suede/",
    "image": "https://media-photos.depop.com/b1/34544665/3020548832_69dbbb5180834b43a63b1fef382af78c/P0.jpg",
    "description": "Brown faux fur lined suede jacket with a boho vibe #fauxfurjacket\nSoo cute for fall\nMESSAGE me before you buy so I can un boost the listing!! Thanks - Sold by @shopy2z",
    "category": "outerwear",
    "tag": "Depop find"
  },
  {
    "title": "Reebok lookalike black and blue windbreaker shell...",
    "price": "",
    "url": "https://www.depop.com/products/zoessorenson-reebok-lookalike-black-and-blue/",
    "image": "https://media-photos.depop.com/b1/34544665/3030463005_948aabb0aa60413b814c8bcc73119aa2/P0.jpg",
    "description": "Reebok lookalike black and blue windbreaker shell jacket jacket - Sold by @shopy2z",
    "category": "outerwear",
    "tag": "Depop find"
  },
  {
    "title": "Cute y2k butterfly shirt",
    "price": "",
    "url": "https://www.depop.com/products/zoessorenson-cute-y2k-butterfly-shirt/",
    "image": "https://media-photos.depop.com/b1/34544665/2951926159_380e1e399a6f4d68a68da96378778432/P0.jpg",
    "description": "Cute y2k butterfly shirt - Sold by @shopy2z",
    "category": "tops",
    "tag": "Depop find"
  },
  {
    "title": "North face shell jacket.\nI\u2019m 5\u201d5 and size Small/Med...",
    "price": "",
    "url": "https://www.depop.com/products/zoessorenson-north-face-shell-jacket-im/",
    "image": "https://media-photos.depop.com/b1/34544665/2923294816_6383d9938fbb4e34955681c1751e32a9/P0.jpg",
    "description": "North face shell jacket.\nI\u2019m 5\u201d5 and size Small/Med for reference.\nSize Med.\nFleece insulation. - Sold by @shopy2z",
    "category": "outerwear",
    "tag": "Depop find"
  },
  {
    "title": "Charlotte Russe mini pattern dress\nFits size Xs, S",
    "price": "",
    "url": "https://www.depop.com/products/zoessorenson-charlotte-russe-mini-pattern-dress/",
    "image": "https://media-photos.depop.com/b1/34544665/2869473930_5a23408df89e454885deb69930a186fe/P0.jpg",
    "description": "Charlotte Russe mini pattern dress\nFits size Xs, S - Sold by @shopy2z",
    "category": "tops",
    "tag": "Depop find"
  },
  {
    "title": "Pink and navy wrangler denim shorts \n5/6 x 34 \n26\u201d...",
    "price": "",
    "url": "https://www.depop.com/products/zoessorenson-pink-and-navy-wrangler-denim/",
    "image": "https://media-photos.depop.com/b1/34544665/2869461800_2b164fbccd1a47498b0b505bf1d5cfcf/P0.jpg",
    "description": "Pink and navy wrangler denim shorts \n5/6 x 34 \n26\u201d waist - Sold by @shopy2z",
    "category": "bottoms",
    "tag": "Depop find"
  },
  {
    "title": "Pacsun crew \nOversized \nComfy",
    "price": "",
    "url": "https://www.depop.com/products/zoesss-pacsun-crew-oversized-comfy/",
    "image": "https://media-photos.depop.com/b1/34544665/2393536032_288d7bf6b876421d85a739552a6216fa/P0.jpg",
    "description": "Pacsun crew \nOversized \nComfy - Sold by @shopy2z",
    "category": "tops",
    "tag": "Depop find"
  }
]